spacy_pytorch_transformers/__init__.py
spacy_pytorch_transformers/_tokenizers.py
spacy_pytorch_transformers/_train.py
spacy_pytorch_transformers/about.py
spacy_pytorch_transformers/activations.py
spacy_pytorch_transformers/hyper_params.py
spacy_pytorch_transformers/language.py
spacy_pytorch_transformers/model_registry.py
spacy_pytorch_transformers/pipeline.py
spacy_pytorch_transformers/tok2vec.py
spacy_pytorch_transformers/util.py
spacy_pytorch_transformers/wordpiecer.py
spacy_pytorch_transformers/wrapper.py
spacy_pytorch_transformers/_extra/__init__.py
spacy_pytorch_transformers/_extra/glue_tasks.py
spacy_pytorch_transformers/_extra/hyper_params.py
spacy_pytorch_transformers/pipeline/__init__.py
spacy_pytorch_transformers/pipeline/textcat.py
spacy_pytorch_transformers/pipeline/tok2vec.py
spacy_pytorch_transformers/pipeline/wordpiecer.py
tests/__init__.py
tests/conftest.py
tests/test_activations.py
tests/test_extensions.py
tests/test_language.py
tests/test_model_registry.py
tests/test_textcat.py
tests/test_tok2vec.py
tests/test_util.py
tests/test_wordpiecer.py
tests/test_wrapper.py
tests/util.py
spacy_pytorch_transformers-0.4.0.dist-info/LICENSE
spacy_pytorch_transformers-0.4.0.dist-info/METADATA
spacy_pytorch_transformers-0.4.0.dist-info/WHEEL
spacy_pytorch_transformers-0.4.0.dist-info/entry_points.txt
spacy_pytorch_transformers-0.4.0.dist-info/top_level.txt
spacy_pytorch_transformers-0.4.0.dist-info/RECORD
