Metadata-Version: 2.1
Name: spacy-pytorch-transformers
Version: 0.4.0
Summary: spaCy pipelines for pre-trained BERT and other transformers
Home-page: https://explosion.ai
Author: Explosion
Author-email: contact@explosion.ai
License: MIT
Platform: UNKNOWN
Classifier: Development Status :: 4 - Beta
Classifier: Intended Audience :: Developers
Classifier: Topic :: Scientific/Engineering :: Artificial Intelligence
Classifier: Programming Language :: Python :: 3.6
Classifier: Programming Language :: Python :: 3.7
Requires-Python: >=3.6
Requires-Dist: spacy (<2.2.0,>=2.1.7)
Requires-Dist: pytorch-transformers (<1.3.0,>=1.2.0)
Requires-Dist: torch (>=1.0.0)
Requires-Dist: torchcontrib (<0.1.0,>=0.0.2)
Requires-Dist: srsly (<1.1.0,>=0.0.7)
Requires-Dist: ftfy (<6.0.0,>=5.0.0)
Requires-Dist: dataclasses (<0.7,>=0.6) ; python_version < "3.7"
Provides-Extra: cuda
Requires-Dist: thinc-gpu-ops (<0.1.0,>=0.0.1) ; extra == 'cuda'
Requires-Dist: cupy (>=5.0.0b4) ; extra == 'cuda'
Provides-Extra: cuda100
Requires-Dist: thinc-gpu-ops (<0.1.0,>=0.0.1) ; extra == 'cuda100'
Requires-Dist: cupy-cuda100 (>=5.0.0b4) ; extra == 'cuda100'
Provides-Extra: cuda80
Requires-Dist: thinc-gpu-ops (<0.1.0,>=0.0.1) ; extra == 'cuda80'
Requires-Dist: cupy-cuda80 (>=5.0.0b4) ; extra == 'cuda80'
Provides-Extra: cuda90
Requires-Dist: thinc-gpu-ops (<0.1.0,>=0.0.1) ; extra == 'cuda90'
Requires-Dist: cupy-cuda90 (>=5.0.0b4) ; extra == 'cuda90'
Provides-Extra: cuda91
Requires-Dist: thinc-gpu-ops (<0.1.0,>=0.0.1) ; extra == 'cuda91'
Requires-Dist: cupy-cuda91 (>=5.0.0b4) ; extra == 'cuda91'
Provides-Extra: cuda92
Requires-Dist: thinc-gpu-ops (<0.1.0,>=0.0.1) ; extra == 'cuda92'
Requires-Dist: cupy-cuda92 (>=5.0.0b4) ; extra == 'cuda92'
